coininfo_vasile/__init__.py
coininfo_vasile/info.py
coininfo_vasile-1.0.1.dist-info/METADATA
coininfo_vasile-1.0.1.dist-info/WHEEL
coininfo_vasile-1.0.1.dist-info/top_level.txt
coininfo_vasile-1.0.1.dist-info/RECORD
